pygitmirror/__init__.py
pygitmirror/__main__.py
pygitmirror/py.typed
pygitmirror/arguments/__init__.py
pygitmirror/arguments/arguments.py
pygitmirror/arguments/check_repos.py
pygitmirror/arguments/check_url.py
pygitmirror/arguments/process_arguments.py
pygitmirror/arguments/py.typed
pygitmirror/arguments/read_json.py
pygitmirror/sync/__init__.py
pygitmirror/sync/add_destination_remote.py
pygitmirror/sync/clone_repo.py
pygitmirror/sync/constants.py
pygitmirror/sync/fetch_repo.py
pygitmirror/sync/get_reference_by_name.py
pygitmirror/sync/push_origin_destination.py
pygitmirror/sync/py.typed
pygitmirror/sync/sync_repo.py
pygitmirror-0.0.2.dist-info/LICENSE
pygitmirror-0.0.2.dist-info/METADATA
pygitmirror-0.0.2.dist-info/WHEEL
pygitmirror-0.0.2.dist-info/entry_points.txt
pygitmirror-0.0.2.dist-info/top_level.txt
pygitmirror-0.0.2.dist-info/RECORD
