Metadata-Version: 2.1
Name: pygitmirror
Version: 0.0.2
Summary: An executable to clone git repos from one git server to another.
Author-email: Bassem Girgis <brgirgis@gmail.com>
Maintainer-email: Bassem Girgis <brgirgis@gmail.com>
License: MIT
Project-URL: Homepage, https://github.com/pygitmirror/pygitmirror
Project-URL: Documentation, https://github.com/pygitmirror/pygitmirror
Project-URL: Repository, https://github.com/pygitmirror/pygitmirror.git
Project-URL: Issues, https://github.com/pygitmirror/pygitmirror/issues
Keywords: git,clone,gitea,github,gitlab,mirror,server
Classifier: Development Status :: 5 - Production/Stable
Classifier: Environment :: Console
Classifier: Operating System :: Microsoft :: Windows
Classifier: Operating System :: POSIX :: Linux
Classifier: Operating System :: MacOS
Classifier: License :: OSI Approved :: MIT License
Classifier: Programming Language :: Python :: 3.9
Classifier: Programming Language :: Python :: 3.10
Classifier: Programming Language :: Python :: 3.11
Classifier: Programming Language :: Python :: 3.12
Requires-Python: >=3.9
License-File: LICENSE
Requires-Dist: GitPython
Provides-Extra: dev
Requires-Dist: build ; extra == 'dev'
Requires-Dist: flake8 ; extra == 'dev'
Requires-Dist: mypy ; extra == 'dev'
Requires-Dist: pytest ; extra == 'dev'
Requires-Dist: twine ; extra == 'dev'
Requires-Dist: pylint ; extra == 'dev'
